azure/mgmt/datalake/store/__init__.py
azure/mgmt/datalake/store/data_lake_store_account_management_client.py
azure/mgmt/datalake/store/version.py
azure/mgmt/datalake/store/models/__init__.py
azure/mgmt/datalake/store/models/capability_information.py
azure/mgmt/datalake/store/models/check_name_availability_parameters.py
azure/mgmt/datalake/store/models/create_data_lake_store_account_parameters.py
azure/mgmt/datalake/store/models/create_firewall_rule_with_account_parameters.py
azure/mgmt/datalake/store/models/create_or_update_firewall_rule_parameters.py
azure/mgmt/datalake/store/models/create_or_update_trusted_id_provider_parameters.py
azure/mgmt/datalake/store/models/create_trusted_id_provider_with_account_parameters.py
azure/mgmt/datalake/store/models/data_lake_store_account.py
azure/mgmt/datalake/store/models/data_lake_store_account_basic.py
azure/mgmt/datalake/store/models/data_lake_store_account_basic_paged.py
azure/mgmt/datalake/store/models/data_lake_store_account_management_client_enums.py
azure/mgmt/datalake/store/models/encryption_config.py
azure/mgmt/datalake/store/models/encryption_identity.py
azure/mgmt/datalake/store/models/firewall_rule.py
azure/mgmt/datalake/store/models/firewall_rule_paged.py
azure/mgmt/datalake/store/models/key_vault_meta_info.py
azure/mgmt/datalake/store/models/name_availability_information.py
azure/mgmt/datalake/store/models/operation.py
azure/mgmt/datalake/store/models/operation_display.py
azure/mgmt/datalake/store/models/operation_list_result.py
azure/mgmt/datalake/store/models/resource.py
azure/mgmt/datalake/store/models/sub_resource.py
azure/mgmt/datalake/store/models/trusted_id_provider.py
azure/mgmt/datalake/store/models/trusted_id_provider_paged.py
azure/mgmt/datalake/store/models/update_data_lake_store_account_parameters.py
azure/mgmt/datalake/store/models/update_encryption_config.py
azure/mgmt/datalake/store/models/update_firewall_rule_parameters.py
azure_mgmt_datalake_store-0.4.0.dist-info/DESCRIPTION.rst
azure_mgmt_datalake_store-0.4.0.dist-info/METADATA
azure_mgmt_datalake_store-0.4.0.dist-info/RECORD
azure_mgmt_datalake_store-0.4.0.dist-info/WHEEL
azure_mgmt_datalake_store-0.4.0.dist-info/metadata.json
azure_mgmt_datalake_store-0.4.0.dist-info/top_level.txt
