Metadata-Version: 2.0
Name: azure-mgmt-datalake-store
Version: 0.4.0
Summary: Microsoft Azure Data Lake Store Management Client Client Library for Python
Home-page: https://github.com/Azure/azure-sdk-for-python
Author: Microsoft Corporation
Author-email: azpysdkhelp@microsoft.com
License: MIT License
Platform: UNKNOWN
Classifier: Development Status :: 4 - Beta
Classifier: Programming Language :: Python
Classifier: Programming Language :: Python :: 2
Classifier: Programming Language :: Python :: 2.7
Classifier: Programming Language :: Python :: 3
Classifier: Programming Language :: Python :: 3.4
Classifier: Programming Language :: Python :: 3.5
Classifier: Programming Language :: Python :: 3.6
Classifier: License :: OSI Approved :: MIT License
Requires-Dist: msrestazure (<2.0.0,>=0.4.20)
Requires-Dist: azure-common (~=1.1)
Requires-Dist: azure-mgmt-datalake-nspkg (>=2.0.0)
